LICENSE
MANIFEST.in
README.rst
setup.py
django_licensing.egg-info/PKG-INFO
django_licensing.egg-info/SOURCES.txt
django_licensing.egg-info/dependency_links.txt
django_licensing.egg-info/top_level.txt
licensing/__init__.py
licensing/models.py
licensing/test_settings.py
licensing/fixtures/initial_data.json
licensing/locale/ca/LC_MESSAGES/django.po
licensing/locale/de/LC_MESSAGES/django.po
licensing/locale/el/LC_MESSAGES/django.po
licensing/locale/en/LC_MESSAGES/django.po
licensing/locale/es/LC_MESSAGES/django.po
licensing/locale/es_ES/LC_MESSAGES/django.po
licensing/locale/fi/LC_MESSAGES/django.po
licensing/locale/fr/LC_MESSAGES/django.po
licensing/locale/hr/LC_MESSAGES/django.po
licensing/locale/id/LC_MESSAGES/django.po
licensing/locale/is/LC_MESSAGES/django.po
licensing/locale/it/LC_MESSAGES/django.po
licensing/locale/ja/LC_MESSAGES/django.po
licensing/locale/ko/LC_MESSAGES/django.po
licensing/locale/nl/LC_MESSAGES/django.po
licensing/locale/no/LC_MESSAGES/django.po
licensing/locale/pl/LC_MESSAGES/django.po
licensing/locale/pt/LC_MESSAGES/django.po
licensing/locale/pt_BR/LC_MESSAGES/django.po
licensing/locale/ru/LC_MESSAGES/django.po
licensing/locale/sv/LC_MESSAGES/django.po
licensing/locale/uk/LC_MESSAGES/django.po
licensing/locale/zh/LC_MESSAGES/django.po
licensing/locale/zh_TW/LC_MESSAGES/django.po
licensing/migrations/0001_initial.py
licensing/migrations/0002_load_licenses.py
licensing/migrations/__init__.py
licensing/static/licensing/font/openwebicons.eot
licensing/static/licensing/font/openwebicons.svg
licensing/static/licensing/font/openwebicons.ttf
licensing/static/licensing/font/openwebicons.woff
licensing/static/licensing/font/openwebicons.woff2
licensing/templates/__init__.py
licensing/templates/licensing/setup.html
licensing/templates/licensing/symbols.html
licensing/templatetags/__init__.py
licensing/templatetags/licensing_tags.py