Metadata-Version: 2.1
Name: django-licensing
Version: 1.0.4
Summary: A Django model and data for adding licensing info to data.
Home-page: https://github.com/editorsnotes/django-licensing
Author: Ryan Shaw
Author-email: ryanshaw@unc.edu
License: Public Domain
Download-URL: https://github.com/editorsnotes/django-licensing/tarball/1.0.4
Keywords: django,licenses,licences
Platform: UNKNOWN
Classifier: Environment :: Web Environment
Classifier: Framework :: Django
Classifier: Intended Audience :: Developers
Classifier: License :: Public Domain
Classifier: Operating System :: OS Independent
Classifier: Programming Language :: Python
Classifier: Programming Language :: Python :: 3.8
Classifier: Topic :: Internet :: WWW/HTTP
Classifier: Topic :: Internet :: WWW/HTTP :: Dynamic Content
